pytest_errxfail/__init__.py
pytest_errxfail/errxfail.py
pytest_errxfail/matchers.py
pytest_errxfail-0.1.0.dist-info/LICENSE
pytest_errxfail-0.1.0.dist-info/METADATA
pytest_errxfail-0.1.0.dist-info/WHEEL
pytest_errxfail-0.1.0.dist-info/entry_points.txt
pytest_errxfail-0.1.0.dist-info/top_level.txt
pytest_errxfail-0.1.0.dist-info/RECORD
