Metadata-Version: 2.1
Name: pytest-errxfail
Version: 0.1.0
Summary: pytest plugin to mark a test as xfailed if it fails with the specified error message in the captured output
Author-email: eltio <eltio.sw@mail.ru>
Maintainer-email: eltio <eltio.sw@mail.ru>
License: 
Project-URL: Repository, https://github.com/eltimen/pytest-errxfail
Classifier: Framework :: Pytest
Classifier: Development Status :: 4 - Beta
Classifier: Intended Audience :: Developers
Classifier: Topic :: Software Development :: Testing
Classifier: Operating System :: OS Independent
Classifier: Programming Language :: Python
Classifier: Programming Language :: Python :: 3.8
Classifier: Programming Language :: Python :: 3.9
Classifier: Programming Language :: Python :: 3.10
Classifier: Programming Language :: Python :: 3.11
Classifier: Programming Language :: Python :: 3.12
Classifier: Programming Language :: Python :: 3 :: Only
Classifier: Programming Language :: Python :: Implementation :: CPython
Classifier: Programming Language :: Python :: Implementation :: PyPy
Classifier: License :: OSI Approved :: MIT License
Requires-Python: >=3.8
License-File: LICENSE
Requires-Dist: pytest>=6.2.0
